enthusiast_source_sanitycms/__init__.py
enthusiast_source_sanitycms/source.py
enthusiast_source_sanitycms-1.2.0.dist-info/METADATA
enthusiast_source_sanitycms-1.2.0.dist-info/WHEEL
enthusiast_source_sanitycms-1.2.0.dist-info/licenses/LICENCE.md
enthusiast_source_sanitycms-1.2.0.dist-info/RECORD
