Metadata-Version: 2.4
Name: enthusiast-source-sanitycms
Version: 1.2.0
Summary: A plugin for Enthusiast that provides a SanityCMS documents importer.
License-File: LICENCE.md
Author: Kuba Szczęśniak
Author-email: kuba.szczesniak@upsidelab.io
Requires-Python: >=3.10,<4.0
Classifier: Programming Language :: Python :: 3
Classifier: Programming Language :: Python :: 3.10
Classifier: Programming Language :: Python :: 3.11
Classifier: Programming Language :: Python :: 3.12
Classifier: Programming Language :: Python :: 3.13
Classifier: Programming Language :: Python :: 3.14
Requires-Dist: enthusiast-common (>=1.4,<2)
Requires-Dist: requests (>=2.32.3,<3.0.0)
